brainforge_tokenizer/__init__.py
brainforge_tokenizer/tokenizer.py
brainforge_tokenizer/vocab.json
brainforge_tokenizer-1.0.5.dist-info/METADATA
brainforge_tokenizer-1.0.5.dist-info/WHEEL
brainforge_tokenizer-1.0.5.dist-info/top_level.txt
brainforge_tokenizer-1.0.5.dist-info/RECORD
